ultima_schemata/ultima.py
ultima_schemata-0.1.10.dist-info/WHEEL
ultima_schemata-0.1.10.dist-info/METADATA
ultima_schemata-0.1.10.dist-info/RECORD
